{
  "host_groups" : [
    {
      "name" : "master",
      "configurations" : [
        {
          "global" : {
            "nagios_contact": "raov@avalonconsult.com",
            "nagios_web_password": "password"
          }
        }
      ],
      "components" : [
        {
          "name" : "NAMENODE"
        },
        {
          "name" : "SECONDARY_NAMENODE"
        },       
        {
          "name" : "RESOURCEMANAGER"
        },
        {
          "name" : "HISTORYSERVER"
        },
        {
          "name" : "NAGIOS_SERVER"
        },
        {
          "name" : "GANGLIA_SERVER"
        },
        {
          "name" : "APP_TIMELINE_SERVER"
        },
        {
          "name" : "YARN_CLIENT"
        },
        {
          "name" : "HDFS_CLIENT"
        },
        {
          "name" : "ZOOKEEPER_SERVER"
        },
        {
          "name" : "ZOOKEEPER_CLIENT"
        }
      ],
      "cardinality" : "1"
    },
    {
      "name" : "slaves",
      "components" : [
        {
          "name" : "DATANODE"
        },
        {
          "name" : "HDFS_CLIENT"
        },
        {
          "name" : "NODEMANAGER"
        },
        {
          "name" : "YARN_CLIENT"
        },
        {
          "name" : "MAPREDUCE2_CLIENT"
        },
        {
          "name" : "ZOOKEEPER_CLIENT"
        },
        {
          "name" : "GANGLIA_MONITOR"
        }
      ],
      "cardinality" : "2"
    }
  ],
  "Blueprints" : {
    "stack_name" : "HDP",
    "stack_version" : "2.1"
  }
}